TorchCRF/__init__.py
TorchCRF-1.0.8.dist-info/LICENSE
TorchCRF-1.0.8.dist-info/METADATA
TorchCRF-1.0.8.dist-info/WHEEL
TorchCRF-1.0.8.dist-info/top_level.txt
TorchCRF-1.0.8.dist-info/RECORD
