Metadata-Version: 2.1
Name: TorchCRF
Version: 1.0.8
Summary: An Implementation of Conditional Random Fields in pytorch
Home-page: https://github.com/s14t284/TorchCRF
Author: Ryuya Ikeda
Author-email: rikeda71@gmail.com
License: MIT
Keywords: crf,conditional random fields,nlp,natural language processing
Platform: UNKNOWN
Classifier: License :: OSI Approved :: MIT License
Classifier: Programming Language :: Python :: 3.6
Classifier: Programming Language :: Python :: 3.7
Classifier: Programming Language :: Python :: 3.8
Classifier: Topic :: Text Processing
Requires-Dist: numpy
Requires-Dist: torch (>=1.0.0)
